torongoxetu/__init__.py
torongoxetu-1.0.1.dist-info/METADATA
torongoxetu-1.0.1.dist-info/WHEEL
torongoxetu-1.0.1.dist-info/top_level.txt
torongoxetu-1.0.1.dist-info/RECORD
