Metadata-Version: 2.4
Name: torongoxetu
Version: 1.0.1
Summary: A inference library for the TorongoXetu Assamese ASR model.
Author: Anand Dey
Author-email: ananddey.nic@gmail.com
Classifier: Programming Language :: Python :: 3
Classifier: License :: OSI Approved :: MIT License
Classifier: Operating System :: OS Independent
Requires-Python: >=3.8
Requires-Dist: torch
Requires-Dist: numpy
Requires-Dist: soundfile
Dynamic: author
Dynamic: author-email
Dynamic: classifier
Dynamic: description
Dynamic: description-content-type
Dynamic: requires-dist
Dynamic: requires-python
Dynamic: summary
